{
  "schema_version": "1.0",
  "name": "W_Announcer",
  "path": "/Game/FPS_Game/Blueprints/Bonus/Replication/System/COOP/W_Announcer.W_Announcer",
  "type": "Unknown",
  "parent_class": {
    "name": "UserWidget",
    "source": "cpp"
  },
  "capabilities": {
    "has_event_graph": true,
    "has_functions": true,
    "has_variables": true,
    "has_components": false,
    "has_macros": true,
    "has_anim_graph": false,
    "has_widget_tree": true,
    "has_state_machine": false
  },
  "compile_status": "success",
  "graphs": {
    "event_graphs": [
      {
        "name": "EventGraph",
        "graph_type": "EventGraph",
        "node_count": 3,
        "connection_count": 0,
        "page": 0,
        "page_size": 200,
        "total_pages": 1,
        "is_large_graph": false,
        "normalized_params": true,
        "normalized_fields": [
          "path->asset_path"
        ],
        "nodes": [
          {
            "id": "node_0",
            "type": "Event",
            "function": "PreConstruct",
            "owning_class": "UserWidget",
            "pins_out": [
              {
                "name": "OutputDelegate",
                "type": {
                  "category": "delegate"
                }
              },
              {
                "name": "then",
                "type": {
                  "category": "exec"
                },
                "is_exec": true
              },
              {
                "name": "IsDesignTime",
                "type": {
                  "category": "bool"
                }
              }
            ],
            "properties": {
              "IsOverride": "true"
            }
          },
          {
            "id": "node_1",
            "type": "Event",
            "function": "Construct",
            "owning_class": "UserWidget",
            "pins_out": [
              {
                "name": "OutputDelegate",
                "type": {
                  "category": "delegate"
                }
              },
              {
                "name": "then",
                "type": {
                  "category": "exec"
                },
                "is_exec": true
              }
            ],
            "properties": {
              "IsOverride": "true"
            }
          },
          {
            "id": "node_2",
            "type": "Event",
            "function": "Tick",
            "owning_class": "UserWidget",
            "pins_out": [
              {
                "name": "OutputDelegate",
                "type": {
                  "category": "delegate"
                }
              },
              {
                "name": "then",
                "type": {
                  "category": "exec"
                },
                "is_exec": true
              },
              {
                "name": "MyGeometry",
                "type": {
                  "category": "struct",
                  "struct_name": "Geometry"
                }
              },
              {
                "name": "InDeltaTime",
                "type": {
                  "category": "float"
                }
              }
            ],
            "properties": {
              "IsOverride": "true"
            }
          }
        ]
      }
    ],
    "functions": [
      {
        "name": "Get_Wave_Num_Text_0",
        "graph_type": "Function",
        "outputs": [
          {
            "name": "ReturnValue",
            "display_name": "Return Value",
            "type": {
              "category": "text"
            }
          }
        ],
        "access": "public",
        "pure": true,
        "node_count": 11,
        "connection_count": 21,
        "page": 0,
        "page_size": 200,
        "total_pages": 1,
        "is_large_graph": false,
        "normalized_params": true,
        "normalized_fields": [
          "path->asset_path"
        ],
        "nodes": [
          {
            "id": "node_0",
            "type": "FunctionEntry",
            "function": "Get_Wave_Num_Text_0",
            "pins_out": [
              {
                "name": "then",
                "type": {
                  "category": "exec"
                },
                "is_exec": true,
                "connections": [
                  "node_8.execute"
                ]
              }
            ]
          },
          {
            "id": "node_1",
            "type": "FunctionResult",
            "function": "Get_Wave_Num_Text_0",
            "pins_in": [
              {
                "name": "execute",
                "type": {
                  "category": "exec"
                },
                "is_exec": true
              },
              {
                "name": "ReturnValue",
                "type": {
                  "category": "text"
                }
              }
            ]
          },
          {
            "id": "node_2",
            "type": "CallFunction",
            "function": "GetGameState",
            "owning_class": "GameplayStatics",
            "pins_out": [
              {
                "name": "ReturnValue",
                "type": {
                  "category": "object",
                  "class": "GameStateBase"
                },
                "connections": [
                  "node_8.Object"
                ]
              }
            ],
            "properties": {
              "IsPure": "true",
              "IsLatent": "false"
            }
          },
          {
            "id": "node_3",
            "type": "CallFunction",
            "function": "Conv_IntToText",
            "owning_class": "KismetTextLibrary",
            "pins_in": [
              {
                "name": "Value",
                "type": {
                  "category": "int"
                },
                "default": "0"
              },
              {
                "name": "bAlwaysSign",
                "type": {
                  "category": "bool"
                },
                "default": "false"
              },
              {
                "name": "bUseGrouping",
                "type": {
                  "category": "bool"
                },
                "default": "true"
              },
              {
                "name": "MinimumIntegralDigits",
                "type": {
                  "category": "int"
                },
                "default": "1"
              },
              {
                "name": "MaximumIntegralDigits",
                "type": {
                  "category": "int"
                },
                "default": "324"
              }
            ],
            "pins_out": [
              {
                "name": "ReturnValue",
                "type": {
                  "category": "text"
                },
                "connections": [
                  "node_6.InText"
                ]
              }
            ],
            "properties": {
              "IsPure": "true",
              "IsLatent": "false"
            }
          },
          {
            "id": "node_4",
            "type": "CallFunction",
            "function": "Conv_StringToText",
            "owning_class": "KismetTextLibrary",
            "pins_in": [
              {
                "name": "InString",
                "type": {
                  "category": "string"
                }
              }
            ],
            "pins_out": [
              {
                "name": "ReturnValue",
                "type": {
                  "category": "text"
                }
              }
            ],
            "properties": {
              "IsPure": "true",
              "IsLatent": "false"
            }
          },
          {
            "id": "node_5",
            "type": "CallFunction",
            "function": "Concat_StrStr",
            "owning_class": "KismetStringLibrary",
            "pins_in": [
              {
                "name": "A",
                "type": {
                  "category": "string"
                },
                "default": "Wave: "
              },
              {
                "name": "B",
                "type": {
                  "category": "string"
                }
              }
            ],
            "pins_out": [
              {
                "name": "ReturnValue",
                "type": {
                  "category": "string"
                },
                "connections": [
                  "node_4.InString"
                ]
              }
            ],
            "properties": {
              "IsPure": "true",
              "IsLatent": "false"
            }
          },
          {
            "id": "node_6",
            "type": "CallFunction",
            "function": "Conv_TextToString",
            "owning_class": "KismetTextLibrary",
            "pins_in": [
              {
                "name": "InText",
                "type": {
                  "category": "text",
                  "is_reference": true,
                  "is_const": true
                }
              }
            ],
            "pins_out": [
              {
                "name": "ReturnValue",
                "type": {
                  "category": "string"
                },
                "connections": [
                  "node_5.B"
                ]
              }
            ],
            "properties": {
              "IsPure": "true",
              "IsLatent": "false"
            }
          },
          {
            "id": "node_7",
            "type": "FunctionResult",
            "function": "Get_Wave_Num_Text_0",
            "pins_in": [
              {
                "name": "execute",
                "type": {
                  "category": "exec"
                },
                "is_exec": true
              },
              {
                "name": "ReturnValue",
                "type": {
                  "category": "text"
                }
              }
            ]
          },
          {
            "id": "node_8",
            "type": "Cast",
            "title": "Cast To Replicated_GameState_COOP",
            "pins_in": [
              {
                "name": "execute",
                "type": {
                  "category": "exec"
                },
                "is_exec": true
              },
              {
                "name": "Object",
                "type": {
                  "category": "object",
                  "class": "Object"
                }
              }
            ],
            "pins_out": [
              {
                "name": "then",
                "type": {
                  "category": "exec"
                },
                "is_exec": true,
                "connections": [
                  "node_1.execute"
                ]
              },
              {
                "name": "CastFailed",
                "type": {
                  "category": "exec"
                },
                "is_exec": true,
                "connections": [
                  "node_7.execute"
                ]
              },
              {
                "name": "AsReplicated Game State COOP",
                "type": {
                  "category": "object",
                  "class": "Replicated_GameState_COOP_C"
                },
                "connections": [
                  "node_9.self",
                  "node_10.self"
                ]
              }
            ],
            "properties": {
              "TargetClass": "Replicated_GameState_COOP_C",
              "TargetClassPath": "/Game/FPS_Game/Blueprints/Bonus/Replication/System/COOP/Replicated_GameState_COOP.Replicated_GameState_COOP_C"
            }
          },
          {
            "id": "node_9",
            "type": "VariableGet",
            "variable": "CurrentWave",
            "pins_in": [
              {
                "name": "self",
                "type": {
                  "category": "object",
                  "class": "Replicated_GameState_COOP_C"
                }
              }
            ],
            "pins_out": [
              {
                "name": "CurrentWave",
                "type": {
                  "category": "int"
                },
                "connections": [
                  "node_3.Value"
                ]
              }
            ],
            "properties": {
              "Scope": "Replicated_GameState_COOP_C"
            }
          },
          {
            "id": "node_10",
            "type": "VariableGet",
            "variable": "Wave Name",
            "pins_in": [
              {
                "name": "self",
                "type": {
                  "category": "object",
                  "class": "Replicated_GameState_COOP_C"
                }
              }
            ],
            "pins_out": [
              {
                "name": "Wave Name",
                "type": {
                  "category": "text"
                },
                "connections": [
                  "node_1.ReturnValue"
                ]
              }
            ],
            "properties": {
              "Scope": "Replicated_GameState_COOP_C"
            }
          }
        ]
      },
      {
        "name": "GetPercent_0",
        "graph_type": "Function",
        "outputs": [
          {
            "name": "ReturnValue",
            "display_name": "Return Value",
            "type": {
              "category": "float"
            }
          }
        ],
        "access": "public",
        "pure": true,
        "node_count": 9,
        "connection_count": 19,
        "page": 0,
        "page_size": 200,
        "total_pages": 1,
        "is_large_graph": false,
        "normalized_params": true,
        "normalized_fields": [
          "path->asset_path"
        ],
        "nodes": [
          {
            "id": "node_0",
            "type": "FunctionEntry",
            "function": "GetPercent_0",
            "pins_out": [
              {
                "name": "then",
                "type": {
                  "category": "exec"
                },
                "is_exec": true,
                "connections": [
                  "node_6.execute"
                ]
              }
            ]
          },
          {
            "id": "node_1",
            "type": "FunctionResult",
            "function": "GetPercent_0",
            "pins_in": [
              {
                "name": "execute",
                "type": {
                  "category": "exec"
                },
                "is_exec": true
              },
              {
                "name": "ReturnValue",
                "type": {
                  "category": "float"
                },
                "default": "0.0"
              }
            ]
          },
          {
            "id": "node_2",
            "type": "CallFunction",
            "function": "GetGameState",
            "owning_class": "GameplayStatics",
            "pins_out": [
              {
                "name": "ReturnValue",
                "type": {
                  "category": "object",
                  "class": "GameStateBase"
                },
                "connections": [
                  "node_6.Object"
                ]
              }
            ],
            "properties": {
              "IsPure": "true",
              "IsLatent": "false"
            }
          },
          {
            "id": "node_3",
            "type": "CallFunction",
            "function": "Conv_IntToDouble",
            "owning_class": "KismetMathLibrary",
            "pins_in": [
              {
                "name": "InInt",
                "type": {
                  "category": "int"
                },
                "default": "0"
              }
            ],
            "pins_out": [
              {
                "name": "ReturnValue",
                "type": {
                  "category": "float"
                },
                "connections": [
                  "node_5.A"
                ]
              }
            ],
            "properties": {
              "IsPure": "true",
              "IsLatent": "false"
            }
          },
          {
            "id": "node_4",
            "type": "CallFunction",
            "function": "Conv_IntToDouble",
            "owning_class": "KismetMathLibrary",
            "pins_in": [
              {
                "name": "InInt",
                "type": {
                  "category": "int"
                },
                "default": "0"
              }
            ],
            "pins_out": [
              {
                "name": "ReturnValue",
                "type": {
                  "category": "float"
                },
                "connections": [
                  "node_5.B"
                ]
              }
            ],
            "properties": {
              "IsPure": "true",
              "IsLatent": "false"
            }
          },
          {
            "id": "node_5",
            "type": "CallFunction",
            "function": "Divide_DoubleDouble",
            "owning_class": "KismetMathLibrary",
            "pins_in": [
              {
                "name": "A",
                "type": {
                  "category": "float"
                },
                "default": "0.0"
              },
              {
                "name": "B",
                "type": {
                  "category": "float"
                },
                "default": "1.000000"
              }
            ],
            "pins_out": [
              {
                "name": "ReturnValue",
                "type": {
                  "category": "float"
                },
                "connections": [
                  "node_1.ReturnValue"
                ]
              }
            ],
            "properties": {
              "IsPure": "true",
              "IsLatent": "false"
            }
          },
          {
            "id": "node_6",
            "type": "Cast",
            "title": "Cast To Replicated_GameState_COOP",
            "pins_in": [
              {
                "name": "execute",
                "type": {
                  "category": "exec"
                },
                "is_exec": true
              },
              {
                "name": "Object",
                "type": {
                  "category": "object",
                  "class": "Object"
                }
              }
            ],
            "pins_out": [
              {
                "name": "then",
                "type": {
                  "category": "exec"
                },
                "is_exec": true,
                "connections": [
                  "node_1.execute"
                ]
              },
              {
                "name": "CastFailed",
                "type": {
                  "category": "exec"
                },
                "is_exec": true
              },
              {
                "name": "AsReplicated Game State COOP",
                "type": {
                  "category": "object",
                  "class": "Replicated_GameState_COOP_C"
                },
                "connections": [
                  "node_7.self",
                  "node_8.self"
                ]
              }
            ],
            "properties": {
              "TargetClass": "Replicated_GameState_COOP_C",
              "TargetClassPath": "/Game/FPS_Game/Blueprints/Bonus/Replication/System/COOP/Replicated_GameState_COOP.Replicated_GameState_COOP_C"
            }
          },
          {
            "id": "node_7",
            "type": "VariableGet",
            "variable": "EnemiesRequired_Current",
            "pins_in": [
              {
                "name": "self",
                "type": {
                  "category": "object",
                  "class": "Replicated_GameState_COOP_C"
                }
              }
            ],
            "pins_out": [
              {
                "name": "EnemiesRequired_Current",
                "type": {
                  "category": "int"
                },
                "connections": [
                  "node_3.InInt"
                ]
              }
            ],
            "properties": {
              "Scope": "Replicated_GameState_COOP_C"
            }
          },
          {
            "id": "node_8",
            "type": "VariableGet",
            "variable": "EnemiesRequired_DefaultValue",
            "pins_in": [
              {
                "name": "self",
                "type": {
                  "category": "object",
                  "class": "Replicated_GameState_COOP_C"
                }
              }
            ],
            "pins_out": [
              {
                "name": "EnemiesRequired_DefaultValue",
                "type": {
                  "category": "int"
                },
                "connections": [
                  "node_4.InInt"
                ]
              }
            ],
            "properties": {
              "Scope": "Replicated_GameState_COOP_C"
            }
          }
        ]
      },
      {
        "name": "GetText_Kills",
        "graph_type": "Function",
        "outputs": [
          {
            "name": "ReturnValue",
            "display_name": "Return Value",
            "type": {
              "category": "text"
            }
          }
        ],
        "access": "public",
        "pure": true,
        "node_count": 8,
        "connection_count": 16,
        "page": 0,
        "page_size": 200,
        "total_pages": 1,
        "is_large_graph": false,
        "normalized_params": true,
        "normalized_fields": [
          "path->asset_path"
        ],
        "nodes": [
          {
            "id": "node_0",
            "type": "FunctionEntry",
            "function": "GetText_Kills",
            "pins_out": [
              {
                "name": "then",
                "type": {
                  "category": "exec"
                },
                "is_exec": true,
                "connections": [
                  "node_6.execute"
                ]
              }
            ]
          },
          {
            "id": "node_1",
            "type": "FunctionResult",
            "function": "GetText_Kills",
            "pins_in": [
              {
                "name": "execute",
                "type": {
                  "category": "exec"
                },
                "is_exec": true
              },
              {
                "name": "ReturnValue",
                "type": {
                  "category": "text"
                }
              }
            ]
          },
          {
            "id": "node_2",
            "type": "CallFunction",
            "function": "GetGameState",
            "owning_class": "GameplayStatics",
            "pins_out": [
              {
                "name": "ReturnValue",
                "type": {
                  "category": "object",
                  "class": "GameStateBase"
                },
                "connections": [
                  "node_6.Object"
                ]
              }
            ],
            "properties": {
              "IsPure": "true",
              "IsLatent": "false"
            }
          },
          {
            "id": "node_3",
            "type": "CallFunction",
            "function": "Conv_StringToText",
            "owning_class": "KismetTextLibrary",
            "pins_in": [
              {
                "name": "InString",
                "type": {
                  "category": "string"
                }
              }
            ],
            "pins_out": [
              {
                "name": "ReturnValue",
                "type": {
                  "category": "text"
                },
                "connections": [
                  "node_1.ReturnValue"
                ]
              }
            ],
            "properties": {
              "IsPure": "true",
              "IsLatent": "false"
            }
          },
          {
            "id": "node_4",
            "type": "CallFunction",
            "function": "Concat_StrStr",
            "owning_class": "KismetStringLibrary",
            "pins_in": [
              {
                "name": "A",
                "type": {
                  "category": "string"
                },
                "default": "Total enemies killed: "
              },
              {
                "name": "B",
                "type": {
                  "category": "string"
                }
              }
            ],
            "pins_out": [
              {
                "name": "ReturnValue",
                "type": {
                  "category": "string"
                },
                "connections": [
                  "node_3.InString"
                ]
              }
            ],
            "properties": {
              "IsPure": "true",
              "IsLatent": "false"
            }
          },
          {
            "id": "node_5",
            "type": "CallFunction",
            "function": "Conv_IntToString",
            "owning_class": "KismetStringLibrary",
            "pins_in": [
              {
                "name": "InInt",
                "type": {
                  "category": "int"
                },
                "default": "0"
              }
            ],
            "pins_out": [
              {
                "name": "ReturnValue",
                "type": {
                  "category": "string"
                },
                "connections": [
                  "node_4.B"
                ]
              }
            ],
            "properties": {
              "IsPure": "true",
              "IsLatent": "false"
            }
          },
          {
            "id": "node_6",
            "type": "Cast",
            "title": "Cast To Replicated_GameState_COOP",
            "pins_in": [
              {
                "name": "execute",
                "type": {
                  "category": "exec"
                },
                "is_exec": true
              },
              {
                "name": "Object",
                "type": {
                  "category": "object",
                  "class": "Object"
                }
              }
            ],
            "pins_out": [
              {
                "name": "then",
                "type": {
                  "category": "exec"
                },
                "is_exec": true,
                "connections": [
                  "node_1.execute"
                ]
              },
              {
                "name": "CastFailed",
                "type": {
                  "category": "exec"
                },
                "is_exec": true
              },
              {
                "name": "AsReplicated Game State COOP",
                "type": {
                  "category": "object",
                  "class": "Replicated_GameState_COOP_C"
                },
                "connections": [
                  "node_7.self"
                ]
              }
            ],
            "properties": {
              "TargetClass": "Replicated_GameState_COOP_C",
              "TargetClassPath": "/Game/FPS_Game/Blueprints/Bonus/Replication/System/COOP/Replicated_GameState_COOP.Replicated_GameState_COOP_C"
            }
          },
          {
            "id": "node_7",
            "type": "VariableGet",
            "variable": "EnemiesKilled",
            "pins_in": [
              {
                "name": "self",
                "type": {
                  "category": "object",
                  "class": "Replicated_GameState_COOP_C"
                }
              }
            ],
            "pins_out": [
              {
                "name": "EnemiesKilled",
                "type": {
                  "category": "int"
                },
                "connections": [
                  "node_5.InInt"
                ]
              }
            ],
            "properties": {
              "Scope": "Replicated_GameState_COOP_C"
            }
          }
        ]
      },
      {
        "name": "GetText_Score",
        "graph_type": "Function",
        "outputs": [
          {
            "name": "ReturnValue",
            "display_name": "Return Value",
            "type": {
              "category": "text"
            }
          }
        ],
        "access": "public",
        "pure": true,
        "node_count": 8,
        "connection_count": 16,
        "page": 0,
        "page_size": 200,
        "total_pages": 1,
        "is_large_graph": false,
        "normalized_params": true,
        "normalized_fields": [
          "path->asset_path"
        ],
        "nodes": [
          {
            "id": "node_0",
            "type": "FunctionEntry",
            "function": "GetText_Score",
            "pins_out": [
              {
                "name": "then",
                "type": {
                  "category": "exec"
                },
                "is_exec": true,
                "connections": [
                  "node_6.execute"
                ]
              }
            ]
          },
          {
            "id": "node_1",
            "type": "FunctionResult",
            "function": "GetText_Score",
            "pins_in": [
              {
                "name": "execute",
                "type": {
                  "category": "exec"
                },
                "is_exec": true
              },
              {
                "name": "ReturnValue",
                "type": {
                  "category": "text"
                }
              }
            ]
          },
          {
            "id": "node_2",
            "type": "CallFunction",
            "function": "GetGameState",
            "owning_class": "GameplayStatics",
            "pins_out": [
              {
                "name": "ReturnValue",
                "type": {
                  "category": "object",
                  "class": "GameStateBase"
                },
                "connections": [
                  "node_6.Object"
                ]
              }
            ],
            "properties": {
              "IsPure": "true",
              "IsLatent": "false"
            }
          },
          {
            "id": "node_3",
            "type": "CallFunction",
            "function": "Conv_StringToText",
            "owning_class": "KismetTextLibrary",
            "pins_in": [
              {
                "name": "InString",
                "type": {
                  "category": "string"
                }
              }
            ],
            "pins_out": [
              {
                "name": "ReturnValue",
                "type": {
                  "category": "text"
                },
                "connections": [
                  "node_1.ReturnValue"
                ]
              }
            ],
            "properties": {
              "IsPure": "true",
              "IsLatent": "false"
            }
          },
          {
            "id": "node_4",
            "type": "CallFunction",
            "function": "Concat_StrStr",
            "owning_class": "KismetStringLibrary",
            "pins_in": [
              {
                "name": "A",
                "type": {
                  "category": "string"
                },
                "default": "Score: "
              },
              {
                "name": "B",
                "type": {
                  "category": "string"
                }
              }
            ],
            "pins_out": [
              {
                "name": "ReturnValue",
                "type": {
                  "category": "string"
                },
                "connections": [
                  "node_3.InString"
                ]
              }
            ],
            "properties": {
              "IsPure": "true",
              "IsLatent": "false"
            }
          },
          {
            "id": "node_5",
            "type": "CallFunction",
            "function": "Conv_IntToString",
            "owning_class": "KismetStringLibrary",
            "pins_in": [
              {
                "name": "InInt",
                "type": {
                  "category": "int"
                },
                "default": "0"
              }
            ],
            "pins_out": [
              {
                "name": "ReturnValue",
                "type": {
                  "category": "string"
                },
                "connections": [
                  "node_4.B"
                ]
              }
            ],
            "properties": {
              "IsPure": "true",
              "IsLatent": "false"
            }
          },
          {
            "id": "node_6",
            "type": "Cast",
            "title": "Cast To Replicated_GameState_COOP",
            "pins_in": [
              {
                "name": "execute",
                "type": {
                  "category": "exec"
                },
                "is_exec": true
              },
              {
                "name": "Object",
                "type": {
                  "category": "object",
                  "class": "Object"
                }
              }
            ],
            "pins_out": [
              {
                "name": "then",
                "type": {
                  "category": "exec"
                },
                "is_exec": true,
                "connections": [
                  "node_1.execute"
                ]
              },
              {
                "name": "CastFailed",
                "type": {
                  "category": "exec"
                },
                "is_exec": true
              },
              {
                "name": "AsReplicated Game State COOP",
                "type": {
                  "category": "object",
                  "class": "Replicated_GameState_COOP_C"
                },
                "connections": [
                  "node_7.self"
                ]
              }
            ],
            "properties": {
              "TargetClass": "Replicated_GameState_COOP_C",
              "TargetClassPath": "/Game/FPS_Game/Blueprints/Bonus/Replication/System/COOP/Replicated_GameState_COOP.Replicated_GameState_COOP_C"
            }
          },
          {
            "id": "node_7",
            "type": "VariableGet",
            "variable": "CurrentScore",
            "pins_in": [
              {
                "name": "self",
                "type": {
                  "category": "object",
                  "class": "Replicated_GameState_COOP_C"
                }
              }
            ],
            "pins_out": [
              {
                "name": "CurrentScore",
                "type": {
                  "category": "int"
                },
                "connections": [
                  "node_5.InInt"
                ]
              }
            ],
            "properties": {
              "Scope": "Replicated_GameState_COOP_C"
            }
          }
        ]
      },
      {
        "name": "Get_TimeLeft_TXT_Text_0",
        "graph_type": "Function",
        "outputs": [
          {
            "name": "ReturnValue",
            "display_name": "Return Value",
            "type": {
              "category": "text"
            }
          }
        ],
        "access": "public",
        "pure": true,
        "node_count": 9,
        "connection_count": 18,
        "page": 0,
        "page_size": 200,
        "total_pages": 1,
        "is_large_graph": false,
        "normalized_params": true,
        "normalized_fields": [
          "path->asset_path"
        ],
        "nodes": [
          {
            "id": "node_0",
            "type": "FunctionEntry",
            "function": "Get_TimeLeft_TXT_Text_0",
            "pins_out": [
              {
                "name": "then",
                "type": {
                  "category": "exec"
                },
                "is_exec": true,
                "connections": [
                  "node_7.execute"
                ]
              }
            ]
          },
          {
            "id": "node_1",
            "type": "FunctionResult",
            "function": "Get_TimeLeft_TXT_Text_0",
            "pins_in": [
              {
                "name": "execute",
                "type": {
                  "category": "exec"
                },
                "is_exec": true
              },
              {
                "name": "ReturnValue",
                "type": {
                  "category": "text"
                }
              }
            ]
          },
          {
            "id": "node_2",
            "type": "CallFunction",
            "function": "GetGameState",
            "owning_class": "GameplayStatics",
            "pins_out": [
              {
                "name": "ReturnValue",
                "type": {
                  "category": "object",
                  "class": "GameStateBase"
                },
                "connections": [
                  "node_7.Object"
                ]
              }
            ],
            "properties": {
              "IsPure": "true",
              "IsLatent": "false"
            }
          },
          {
            "id": "node_3",
            "type": "CallFunction",
            "function": "Conv_IntToText",
            "owning_class": "KismetTextLibrary",
            "pins_in": [
              {
                "name": "Value",
                "type": {
                  "category": "int"
                },
                "default": "0"
              },
              {
                "name": "bAlwaysSign",
                "type": {
                  "category": "bool"
                },
                "default": "false"
              },
              {
                "name": "bUseGrouping",
                "type": {
                  "category": "bool"
                },
                "default": "true"
              },
              {
                "name": "MinimumIntegralDigits",
                "type": {
                  "category": "int"
                },
                "default": "1"
              },
              {
                "name": "MaximumIntegralDigits",
                "type": {
                  "category": "int"
                },
                "default": "324"
              }
            ],
            "pins_out": [
              {
                "name": "ReturnValue",
                "type": {
                  "category": "text"
                },
                "connections": [
                  "node_6.InText"
                ]
              }
            ],
            "properties": {
              "IsPure": "true",
              "IsLatent": "false"
            }
          },
          {
            "id": "node_4",
            "type": "CallFunction",
            "function": "Conv_StringToText",
            "owning_class": "KismetTextLibrary",
            "pins_in": [
              {
                "name": "InString",
                "type": {
                  "category": "string"
                }
              }
            ],
            "pins_out": [
              {
                "name": "ReturnValue",
                "type": {
                  "category": "text"
                },
                "connections": [
                  "node_1.ReturnValue"
                ]
              }
            ],
            "properties": {
              "IsPure": "true",
              "IsLatent": "false"
            }
          },
          {
            "id": "node_5",
            "type": "CallFunction",
            "function": "Concat_StrStr",
            "owning_class": "KismetStringLibrary",
            "pins_in": [
              {
                "name": "A",
                "type": {
                  "category": "string"
                },
                "default": "Remaining time: "
              },
              {
                "name": "B",
                "type": {
                  "category": "string"
                }
              }
            ],
            "pins_out": [
              {
                "name": "ReturnValue",
                "type": {
                  "category": "string"
                },
                "connections": [
                  "node_4.InString"
                ]
              }
            ],
            "properties": {
              "IsPure": "true",
              "IsLatent": "false"
            }
          },
          {
            "id": "node_6",
            "type": "CallFunction",
            "function": "Conv_TextToString",
            "owning_class": "KismetTextLibrary",
            "pins_in": [
              {
                "name": "InText",
                "type": {
                  "category": "text",
                  "is_reference": true,
                  "is_const": true
                }
              }
            ],
            "pins_out": [
              {
                "name": "ReturnValue",
                "type": {
                  "category": "string"
                },
                "connections": [
                  "node_5.B"
                ]
              }
            ],
            "properties": {
              "IsPure": "true",
              "IsLatent": "false"
            }
          },
          {
            "id": "node_7",
            "type": "Cast",
            "title": "Cast To Replicated_GameState_COOP",
            "pins_in": [
              {
                "name": "execute",
                "type": {
                  "category": "exec"
                },
                "is_exec": true
              },
              {
                "name": "Object",
                "type": {
                  "category": "object",
                  "class": "Object"
                }
              }
            ],
            "pins_out": [
              {
                "name": "then",
                "type": {
                  "category": "exec"
                },
                "is_exec": true,
                "connections": [
                  "node_1.execute"
                ]
              },
              {
                "name": "CastFailed",
                "type": {
                  "category": "exec"
                },
                "is_exec": true
              },
              {
                "name": "AsReplicated Game State COOP",
                "type": {
                  "category": "object",
                  "class": "Replicated_GameState_COOP_C"
                },
                "connections": [
                  "node_8.self"
                ]
              }
            ],
            "properties": {
              "TargetClass": "Replicated_GameState_COOP_C",
              "TargetClassPath": "/Game/FPS_Game/Blueprints/Bonus/Replication/System/COOP/Replicated_GameState_COOP.Replicated_GameState_COOP_C"
            }
          },
          {
            "id": "node_8",
            "type": "VariableGet",
            "variable": "RemainingTime",
            "pins_in": [
              {
                "name": "self",
                "type": {
                  "category": "object",
                  "class": "Replicated_GameState_COOP_C"
                }
              }
            ],
            "pins_out": [
              {
                "name": "RemainingTime",
                "type": {
                  "category": "int"
                },
                "connections": [
                  "node_3.Value"
                ]
              }
            ],
            "properties": {
              "Scope": "Replicated_GameState_COOP_C"
            }
          }
        ]
      },
      {
        "name": "Get_Kills_TXT_Text_0",
        "graph_type": "Function",
        "outputs": [
          {
            "name": "ReturnValue",
            "display_name": "Return Value",
            "type": {
              "category": "text"
            }
          }
        ],
        "access": "public",
        "pure": true,
        "node_count": 10,
        "connection_count": 20,
        "page": 0,
        "page_size": 200,
        "total_pages": 1,
        "is_large_graph": false,
        "normalized_params": true,
        "normalized_fields": [
          "path->asset_path"
        ],
        "nodes": [
          {
            "id": "node_0",
            "type": "FunctionEntry",
            "function": "Get_Kills_TXT_Text_0",
            "pins_out": [
              {
                "name": "then",
                "type": {
                  "category": "exec"
                },
                "is_exec": true,
                "connections": [
                  "node_8.execute"
                ]
              }
            ]
          },
          {
            "id": "node_1",
            "type": "FunctionResult",
            "function": "Get_Kills_TXT_Text_0",
            "pins_in": [
              {
                "name": "execute",
                "type": {
                  "category": "exec"
                },
                "is_exec": true
              },
              {
                "name": "ReturnValue",
                "type": {
                  "category": "text"
                }
              }
            ]
          },
          {
            "id": "node_2",
            "type": "CallFunction",
            "function": "GetPlayerController",
            "owning_class": "GameplayStatics",
            "pins_in": [
              {
                "name": "PlayerIndex",
                "type": {
                  "category": "int"
                },
                "default": "0"
              }
            ],
            "pins_out": [
              {
                "name": "ReturnValue",
                "type": {
                  "category": "object",
                  "class": "PlayerController"
                },
                "connections": [
                  "node_3.self"
                ]
              }
            ],
            "properties": {
              "IsPure": "true",
              "IsLatent": "false"
            }
          },
          {
            "id": "node_3",
            "type": "VariableGet",
            "variable": "PlayerState",
            "pins_in": [
              {
                "name": "self",
                "type": {
                  "category": "object",
                  "class": "Controller"
                }
              }
            ],
            "pins_out": [
              {
                "name": "PlayerState",
                "type": {
                  "category": "object",
                  "class": "PlayerState"
                },
                "connections": [
                  "node_8.Object"
                ]
              }
            ],
            "properties": {
              "Scope": "Controller"
            }
          },
          {
            "id": "node_4",
            "type": "CallFunction",
            "function": "Conv_IntToText",
            "owning_class": "KismetTextLibrary",
            "pins_in": [
              {
                "name": "Value",
                "type": {
                  "category": "int"
                },
                "default": "0"
              },
              {
                "name": "bAlwaysSign",
                "type": {
                  "category": "bool"
                },
                "default": "false"
              },
              {
                "name": "bUseGrouping",
                "type": {
                  "category": "bool"
                },
                "default": "true"
              },
              {
                "name": "MinimumIntegralDigits",
                "type": {
                  "category": "int"
                },
                "default": "1"
              },
              {
                "name": "MaximumIntegralDigits",
                "type": {
                  "category": "int"
                },
                "default": "324"
              }
            ],
            "pins_out": [
              {
                "name": "ReturnValue",
                "type": {
                  "category": "text"
                },
                "connections": [
                  "node_7.InText"
                ]
              }
            ],
            "properties": {
              "IsPure": "true",
              "IsLatent": "false"
            }
          },
          {
            "id": "node_5",
            "type": "CallFunction",
            "function": "Conv_StringToText",
            "owning_class": "KismetTextLibrary",
            "pins_in": [
              {
                "name": "InString",
                "type": {
                  "category": "string"
                }
              }
            ],
            "pins_out": [
              {
                "name": "ReturnValue",
                "type": {
                  "category": "text"
                },
                "connections": [
                  "node_1.ReturnValue"
                ]
              }
            ],
            "properties": {
              "IsPure": "true",
              "IsLatent": "false"
            }
          },
          {
            "id": "node_6",
            "type": "CallFunction",
            "function": "Concat_StrStr",
            "owning_class": "KismetStringLibrary",
            "pins_in": [
              {
                "name": "A",
                "type": {
                  "category": "string"
                },
                "default": "Kills: "
              },
              {
                "name": "B",
                "type": {
                  "category": "string"
                }
              }
            ],
            "pins_out": [
              {
                "name": "ReturnValue",
                "type": {
                  "category": "string"
                },
                "connections": [
                  "node_5.InString"
                ]
              }
            ],
            "properties": {
              "IsPure": "true",
              "IsLatent": "false"
            }
          },
          {
            "id": "node_7",
            "type": "CallFunction",
            "function": "Conv_TextToString",
            "owning_class": "KismetTextLibrary",
            "pins_in": [
              {
                "name": "InText",
                "type": {
                  "category": "text",
                  "is_reference": true,
                  "is_const": true
                }
              }
            ],
            "pins_out": [
              {
                "name": "ReturnValue",
                "type": {
                  "category": "string"
                },
                "connections": [
                  "node_6.B"
                ]
              }
            ],
            "properties": {
              "IsPure": "true",
              "IsLatent": "false"
            }
          },
          {
            "id": "node_8",
            "type": "Cast",
            "title": "Cast To Replicated_PlayerState",
            "pins_in": [
              {
                "name": "execute",
                "type": {
                  "category": "exec"
                },
                "is_exec": true
              },
              {
                "name": "Object",
                "type": {
                  "category": "object",
                  "class": "Object"
                }
              }
            ],
            "pins_out": [
              {
                "name": "then",
                "type": {
                  "category": "exec"
                },
                "is_exec": true,
                "connections": [
                  "node_1.execute"
                ]
              },
              {
                "name": "CastFailed",
                "type": {
                  "category": "exec"
                },
                "is_exec": true
              },
              {
                "name": "AsReplicated Player State",
                "type": {
                  "category": "object",
                  "class": "Replicated_PlayerState_C"
                },
                "connections": [
                  "node_9.self"
                ]
              }
            ],
            "properties": {
              "TargetClass": "Replicated_PlayerState_C",
              "TargetClassPath": "/Game/FPS_Game/Blueprints/Bonus/Replication/System/Replicated_PlayerState.Replicated_PlayerState_C"
            }
          },
          {
            "id": "node_9",
            "type": "VariableGet",
            "variable": "NumKills",
            "pins_in": [
              {
                "name": "self",
                "type": {
                  "category": "object",
                  "class": "Replicated_PlayerState_C"
                }
              }
            ],
            "pins_out": [
              {
                "name": "NumKills",
                "type": {
                  "category": "int"
                },
                "connections": [
                  "node_4.Value"
                ]
              }
            ],
            "properties": {
              "Scope": "Replicated_PlayerState_C"
            }
          }
        ]
      },
      {
        "name": "Get_Deaths_TXT_Text_0",
        "graph_type": "Function",
        "outputs": [
          {
            "name": "ReturnValue",
            "display_name": "Return Value",
            "type": {
              "category": "text"
            }
          }
        ],
        "access": "public",
        "pure": true,
        "node_count": 10,
        "connection_count": 20,
        "page": 0,
        "page_size": 200,
        "total_pages": 1,
        "is_large_graph": false,
        "normalized_params": true,
        "normalized_fields": [
          "path->asset_path"
        ],
        "nodes": [
          {
            "id": "node_0",
            "type": "FunctionEntry",
            "function": "Get_Deaths_TXT_Text_0",
            "pins_out": [
              {
                "name": "then",
                "type": {
                  "category": "exec"
                },
                "is_exec": true,
                "connections": [
                  "node_8.execute"
                ]
              }
            ]
          },
          {
            "id": "node_1",
            "type": "FunctionResult",
            "function": "Get_Deaths_TXT_Text_0",
            "pins_in": [
              {
                "name": "execute",
                "type": {
                  "category": "exec"
                },
                "is_exec": true
              },
              {
                "name": "ReturnValue",
                "type": {
                  "category": "text"
                }
              }
            ]
          },
          {
            "id": "node_2",
            "type": "CallFunction",
            "function": "GetPlayerController",
            "owning_class": "GameplayStatics",
            "pins_in": [
              {
                "name": "PlayerIndex",
                "type": {
                  "category": "int"
                },
                "default": "0"
              }
            ],
            "pins_out": [
              {
                "name": "ReturnValue",
                "type": {
                  "category": "object",
                  "class": "PlayerController"
                },
                "connections": [
                  "node_3.self"
                ]
              }
            ],
            "properties": {
              "IsPure": "true",
              "IsLatent": "false"
            }
          },
          {
            "id": "node_3",
            "type": "VariableGet",
            "variable": "PlayerState",
            "pins_in": [
              {
                "name": "self",
                "type": {
                  "category": "object",
                  "class": "Controller"
                }
              }
            ],
            "pins_out": [
              {
                "name": "PlayerState",
                "type": {
                  "category": "object",
                  "class": "PlayerState"
                },
                "connections": [
                  "node_8.Object"
                ]
              }
            ],
            "properties": {
              "Scope": "Controller"
            }
          },
          {
            "id": "node_4",
            "type": "CallFunction",
            "function": "Conv_IntToText",
            "owning_class": "KismetTextLibrary",
            "pins_in": [
              {
                "name": "Value",
                "type": {
                  "category": "int"
                },
                "default": "0"
              },
              {
                "name": "bAlwaysSign",
                "type": {
                  "category": "bool"
                },
                "default": "false"
              },
              {
                "name": "bUseGrouping",
                "type": {
                  "category": "bool"
                },
                "default": "true"
              },
              {
                "name": "MinimumIntegralDigits",
                "type": {
                  "category": "int"
                },
                "default": "1"
              },
              {
                "name": "MaximumIntegralDigits",
                "type": {
                  "category": "int"
                },
                "default": "324"
              }
            ],
            "pins_out": [
              {
                "name": "ReturnValue",
                "type": {
                  "category": "text"
                },
                "connections": [
                  "node_7.InText"
                ]
              }
            ],
            "properties": {
              "IsPure": "true",
              "IsLatent": "false"
            }
          },
          {
            "id": "node_5",
            "type": "CallFunction",
            "function": "Conv_StringToText",
            "owning_class": "KismetTextLibrary",
            "pins_in": [
              {
                "name": "InString",
                "type": {
                  "category": "string"
                }
              }
            ],
            "pins_out": [
              {
                "name": "ReturnValue",
                "type": {
                  "category": "text"
                },
                "connections": [
                  "node_1.ReturnValue"
                ]
              }
            ],
            "properties": {
              "IsPure": "true",
              "IsLatent": "false"
            }
          },
          {
            "id": "node_6",
            "type": "CallFunction",
            "function": "Concat_StrStr",
            "owning_class": "KismetStringLibrary",
            "pins_in": [
              {
                "name": "A",
                "type": {
                  "category": "string"
                },
                "default": "Deaths: "
              },
              {
                "name": "B",
                "type": {
                  "category": "string"
                }
              }
            ],
            "pins_out": [
              {
                "name": "ReturnValue",
                "type": {
                  "category": "string"
                },
                "connections": [
                  "node_5.InString"
                ]
              }
            ],
            "properties": {
              "IsPure": "true",
              "IsLatent": "false"
            }
          },
          {
            "id": "node_7",
            "type": "CallFunction",
            "function": "Conv_TextToString",
            "owning_class": "KismetTextLibrary",
            "pins_in": [
              {
                "name": "InText",
                "type": {
                  "category": "text",
                  "is_reference": true,
                  "is_const": true
                }
              }
            ],
            "pins_out": [
              {
                "name": "ReturnValue",
                "type": {
                  "category": "string"
                },
                "connections": [
                  "node_6.B"
                ]
              }
            ],
            "properties": {
              "IsPure": "true",
              "IsLatent": "false"
            }
          },
          {
            "id": "node_8",
            "type": "Cast",
            "title": "Cast To Replicated_PlayerState",
            "pins_in": [
              {
                "name": "execute",
                "type": {
                  "category": "exec"
                },
                "is_exec": true
              },
              {
                "name": "Object",
                "type": {
                  "category": "object",
                  "class": "Object"
                }
              }
            ],
            "pins_out": [
              {
                "name": "then",
                "type": {
                  "category": "exec"
                },
                "is_exec": true,
                "connections": [
                  "node_1.execute"
                ]
              },
              {
                "name": "CastFailed",
                "type": {
                  "category": "exec"
                },
                "is_exec": true
              },
              {
                "name": "AsReplicated Player State",
                "type": {
                  "category": "object",
                  "class": "Replicated_PlayerState_C"
                },
                "connections": [
                  "node_9.self"
                ]
              }
            ],
            "properties": {
              "TargetClass": "Replicated_PlayerState_C",
              "TargetClassPath": "/Game/FPS_Game/Blueprints/Bonus/Replication/System/Replicated_PlayerState.Replicated_PlayerState_C"
            }
          },
          {
            "id": "node_9",
            "type": "VariableGet",
            "variable": "NumDeaths",
            "pins_in": [
              {
                "name": "self",
                "type": {
                  "category": "object",
                  "class": "Replicated_PlayerState_C"
                }
              }
            ],
            "pins_out": [
              {
                "name": "NumDeaths",
                "type": {
                  "category": "int"
                },
                "connections": [
                  "node_4.Value"
                ]
              }
            ],
            "properties": {
              "Scope": "Replicated_PlayerState_C"
            }
          }
        ]
      },
      {
        "name": "Get_NextWaveTimer_Text_0",
        "graph_type": "Function",
        "outputs": [
          {
            "name": "ReturnValue",
            "display_name": "Return Value",
            "type": {
              "category": "text"
            }
          }
        ],
        "access": "public",
        "pure": true,
        "node_count": 9,
        "connection_count": 17,
        "page": 0,
        "page_size": 200,
        "total_pages": 1,
        "is_large_graph": false,
        "normalized_params": true,
        "normalized_fields": [
          "path->asset_path"
        ],
        "nodes": [
          {
            "id": "node_0",
            "type": "FunctionEntry",
            "function": "Get_NextWaveTimer_Text_0",
            "pins_out": [
              {
                "name": "then",
                "type": {
                  "category": "exec"
                },
                "is_exec": true
              }
            ]
          },
          {
            "id": "node_1",
            "type": "FunctionResult",
            "function": "Get_NextWaveTimer_Text_0",
            "pins_in": [
              {
                "name": "execute",
                "type": {
                  "category": "exec"
                },
                "is_exec": true
              },
              {
                "name": "ReturnValue",
                "type": {
                  "category": "text"
                }
              }
            ]
          },
          {
            "id": "node_2",
            "type": "CallFunction",
            "function": "GetGameState",
            "owning_class": "GameplayStatics",
            "pins_out": [
              {
                "name": "ReturnValue",
                "type": {
                  "category": "object",
                  "class": "GameStateBase"
                },
                "connections": [
                  "node_6.Object"
                ]
              }
            ],
            "properties": {
              "IsPure": "true",
              "IsLatent": "false"
            }
          },
          {
            "id": "node_3",
            "type": "CallFunction",
            "function": "Conv_IntToText",
            "owning_class": "KismetTextLibrary",
            "pins_in": [
              {
                "name": "Value",
                "type": {
                  "category": "int"
                },
                "default": "0"
              },
              {
                "name": "bAlwaysSign",
                "type": {
                  "category": "bool"
                },
                "default": "false"
              },
              {
                "name": "bUseGrouping",
                "type": {
                  "category": "bool"
                },
                "default": "true"
              },
              {
                "name": "MinimumIntegralDigits",
                "type": {
                  "category": "int"
                },
                "default": "1"
              },
              {
                "name": "MaximumIntegralDigits",
                "type": {
                  "category": "int"
                },
                "default": "324"
              }
            ],
            "pins_out": [
              {
                "name": "ReturnValue",
                "type": {
                  "category": "text"
                },
                "connections": [
                  "node_5.Option 1"
                ]
              }
            ],
            "properties": {
              "IsPure": "true",
              "IsLatent": "false"
            }
          },
          {
            "id": "node_4",
            "type": "FunctionResult",
            "function": "Get_NextWaveTimer_Text_0",
            "pins_in": [
              {
                "name": "execute",
                "type": {
                  "category": "exec"
                },
                "is_exec": true
              },
              {
                "name": "ReturnValue",
                "type": {
                  "category": "text"
                }
              }
            ]
          },
          {
            "id": "node_5",
            "type": "K2Node_Select",
            "title": "Select",
            "pins_in": [
              {
                "name": "Option 0",
                "type": {
                  "category": "text"
                }
              },
              {
                "name": "Option 1",
                "type": {
                  "category": "text"
                }
              },
              {
                "name": "Index",
                "type": {
                  "category": "bool"
                },
                "default": "false"
              }
            ],
            "pins_out": [
              {
                "name": "ReturnValue",
                "type": {
                  "category": "text"
                },
                "connections": [
                  "node_1.ReturnValue"
                ]
              }
            ]
          },
          {
            "id": "node_6",
            "type": "Cast",
            "title": "Cast To Replicated_GameState_COOP",
            "pins_in": [
              {
                "name": "execute",
                "type": {
                  "category": "exec"
                },
                "is_exec": true
              },
              {
                "name": "Object",
                "type": {
                  "category": "object",
                  "class": "Object"
                }
              }
            ],
            "pins_out": [
              {
                "name": "then",
                "type": {
                  "category": "exec"
                },
                "is_exec": true,
                "connections": [
                  "node_1.execute"
                ]
              },
              {
                "name": "CastFailed",
                "type": {
                  "category": "exec"
                },
                "is_exec": true,
                "connections": [
                  "node_4.execute"
                ]
              },
              {
                "name": "AsReplicated Game State COOP",
                "type": {
                  "category": "object",
                  "class": "Replicated_GameState_COOP_C"
                },
                "connections": [
                  "node_7.self",
                  "node_8.self"
                ]
              }
            ],
            "properties": {
              "TargetClass": "Replicated_GameState_COOP_C",
              "TargetClassPath": "/Game/FPS_Game/Blueprints/Bonus/Replication/System/COOP/Replicated_GameState_COOP.Replicated_GameState_COOP_C"
            }
          },
          {
            "id": "node_7",
            "type": "VariableGet",
            "variable": "PauseTimer",
            "pins_in": [
              {
                "name": "self",
                "type": {
                  "category": "object",
                  "class": "Replicated_GameState_COOP_C"
                }
              }
            ],
            "pins_out": [
              {
                "name": "PauseTimer",
                "type": {
                  "category": "int"
                },
                "connections": [
                  "node_3.Value"
                ]
              }
            ],
            "properties": {
              "Scope": "Replicated_GameState_COOP_C"
            }
          },
          {
            "id": "node_8",
            "type": "VariableGet",
            "variable": "bTimerPaused",
            "pins_in": [
              {
                "name": "self",
                "type": {
                  "category": "object",
                  "class": "Replicated_GameState_C"
                }
              }
            ],
            "pins_out": [
              {
                "name": "bTimerPaused",
                "type": {
                  "category": "bool"
                },
                "connections": [
                  "node_5.Index"
                ]
              }
            ],
            "properties": {
              "Scope": "Replicated_GameState_C"
            }
          }
        ]
      },
      {
        "name": "Get_NextWaveStartsIn_TXT_Text_0",
        "graph_type": "Function",
        "outputs": [
          {
            "name": "ReturnValue",
            "display_name": "Return Value",
            "type": {
              "category": "text"
            }
          }
        ],
        "access": "public",
        "pure": true,
        "node_count": 7,
        "connection_count": 12,
        "page": 0,
        "page_size": 200,
        "total_pages": 1,
        "is_large_graph": false,
        "normalized_params": true,
        "normalized_fields": [
          "path->asset_path"
        ],
        "nodes": [
          {
            "id": "node_0",
            "type": "FunctionEntry",
            "function": "Get_NextWaveStartsIn_TXT_Text_0",
            "pins_out": [
              {
                "name": "then",
                "type": {
                  "category": "exec"
                },
                "is_exec": true
              }
            ]
          },
          {
            "id": "node_1",
            "type": "FunctionResult",
            "function": "Get_NextWaveStartsIn_TXT_Text_0",
            "pins_in": [
              {
                "name": "execute",
                "type": {
                  "category": "exec"
                },
                "is_exec": true
              },
              {
                "name": "ReturnValue",
                "type": {
                  "category": "text"
                }
              }
            ]
          },
          {
            "id": "node_2",
            "type": "CallFunction",
            "function": "GetGameState",
            "owning_class": "GameplayStatics",
            "pins_out": [
              {
                "name": "ReturnValue",
                "type": {
                  "category": "object",
                  "class": "GameStateBase"
                },
                "connections": [
                  "node_5.Object"
                ]
              }
            ],
            "properties": {
              "IsPure": "true",
              "IsLatent": "false"
            }
          },
          {
            "id": "node_3",
            "type": "K2Node_Select",
            "title": "Select",
            "pins_in": [
              {
                "name": "Option 0",
                "type": {
                  "category": "text"
                }
              },
              {
                "name": "Option 1",
                "type": {
                  "category": "text"
                },
                "default": "Next Wave Starts In..."
              },
              {
                "name": "Index",
                "type": {
                  "category": "bool"
                },
                "default": "false"
              }
            ],
            "pins_out": [
              {
                "name": "ReturnValue",
                "type": {
                  "category": "text"
                },
                "connections": [
                  "node_1.ReturnValue"
                ]
              }
            ]
          },
          {
            "id": "node_4",
            "type": "FunctionResult",
            "function": "Get_NextWaveStartsIn_TXT_Text_0",
            "pins_in": [
              {
                "name": "execute",
                "type": {
                  "category": "exec"
                },
                "is_exec": true
              },
              {
                "name": "ReturnValue",
                "type": {
                  "category": "text"
                }
              }
            ]
          },
          {
            "id": "node_5",
            "type": "Cast",
            "title": "Cast To Replicated_GameState_COOP",
            "pins_in": [
              {
                "name": "execute",
                "type": {
                  "category": "exec"
                },
                "is_exec": true
              },
              {
                "name": "Object",
                "type": {
                  "category": "object",
                  "class": "Object"
                }
              }
            ],
            "pins_out": [
              {
                "name": "then",
                "type": {
                  "category": "exec"
                },
                "is_exec": true,
                "connections": [
                  "node_1.execute"
                ]
              },
              {
                "name": "CastFailed",
                "type": {
                  "category": "exec"
                },
                "is_exec": true,
                "connections": [
                  "node_4.execute"
                ]
              },
              {
                "name": "AsReplicated Game State COOP",
                "type": {
                  "category": "object",
                  "class": "Replicated_GameState_COOP_C"
                },
                "connections": [
                  "node_6.self"
                ]
              }
            ],
            "properties": {
              "TargetClass": "Replicated_GameState_COOP_C",
              "TargetClassPath": "/Game/FPS_Game/Blueprints/Bonus/Replication/System/COOP/Replicated_GameState_COOP.Replicated_GameState_COOP_C"
            }
          },
          {
            "id": "node_6",
            "type": "VariableGet",
            "variable": "bTimerPaused",
            "pins_in": [
              {
                "name": "self",
                "type": {
                  "category": "object",
                  "class": "Replicated_GameState_C"
                }
              }
            ],
            "pins_out": [
              {
                "name": "bTimerPaused",
                "type": {
                  "category": "bool"
                },
                "connections": [
                  "node_3.Index"
                ]
              }
            ],
            "properties": {
              "Scope": "Replicated_GameState_C"
            }
          }
        ]
      }
    ],
    "macros": []
  },
  "normalized_params": true,
  "normalized_fields": [
    "path->asset_path"
  ]
}